src/Join.py
src/Write.py
src/absolute_path.py
src/copy.py
src/csv_image.py
src/csv_image_name.py
src/data_ini.py
src/file_system.py
src/file_to_write.py
src/final_data_csv.py
src/final_data_tag.py
src/group_directory.py
src/group_files.py
src/group_original_files.py
src/group_read_files.py
src/initial_data.py
src/list_tag.py
src/original_file.py
src/personal_logging.py
src/read_file_ini.py
src/safe_directory.py
src/safe_file.py
src/single_final_data.py
src/time_file.py
src/unsafe_file.py
organize_media-1.1.0.dist-info/LICENSE.md
organize_media-1.1.0.dist-info/METADATA
organize_media-1.1.0.dist-info/WHEEL
organize_media-1.1.0.dist-info/entry_points.txt
organize_media-1.1.0.dist-info/top_level.txt
organize_media-1.1.0.dist-info/RECORD
