Metadata-Version: 2.1
Name: organize-media
Version: 1.1.0
Summary: This script copies the media files in the correct path as described by Daniele Carrer
Home-page: http://github.com/alepuzio/organize-media
Author: Alessandro Puzielli aka Alepuzio
Author-email: alessandro.puzielli@alepuzio.net
License: GPL 3
Platform: UNKNOWN
Classifier: Development Status :: 3 - Alpha
Classifier: License :: OSI Approved :: GNU General Public License v3 (GPLv3)
Classifier: Programming Language :: Python :: 3
Classifier: Topic :: Text Processing
Requires-Dist: markdown
